{
    "986313671661727744": {
        "balance": 6614,
        "currency": "<:vboost:1001054517669924904>",
        "bank_balance": 0,
        "bank_limit": 200,
        "work": "\u041e\u0442\u0441\u0443\u0442\u0441\u0442\u0432\u0443\u0435\u0442",
        "skill_hack": 1,
        "skill_protect": 1,
        "business": "PROTOCOL",
        "inventory": {
            "flbedo": 0
        },
        "badges": "<:developer:1000463385558786079> <:vboost:1001054517669924904>"
    },
    "998256502940905542": {
        "balance": 25000,
        "skill_protect": 1
    },
    "563058686239440916": {
        "balance": 1196,
        "currency": "$",
        "bank_balance": 0,
        "bank_limit": 200,
        "work": "\u041e\u0442\u0441\u0443\u0442\u0441\u0442\u0432\u0443\u0435\u0442",
        "skill_protect": 1,
        "skill_hack": 1,
        "business": "\u041e\u0442\u0441\u0443\u0442\u0441\u0442\u0432\u0443\u0435\u0442",
        "inventory": {},
        "badges": "\u041e\u0442\u0441\u0443\u0442\u0441\u0442\u0432\u0443\u044e\u0442"
    },
    "988668120275243008": {
        "1000006398597419050": "1000"
    },
    "PROTOCOL": {
        "ad": 1,
        "building": 1,
        "grafic": "\ud83d\udd3a",
        "balance": 500,
        "workers": 0,
        "stocks": 0,
        "max_stocks": 20,
        "stock_percent": 2,
        "max_workers": 100,
        "stock_price": 10
    },
    "826404981724545034": {
        "balance": 10000,
        "currency": "<:betatester:1001037490477604864>$",
        "bank_balance": 0,
        "bank_limit": 2000,
        "work": "\u041e\u0442\u0441\u0443\u0442\u0441\u0442\u0432\u0443\u0435\u0442",
        "business": "\u041e\u0442\u0441\u0443\u0442\u0441\u0442\u0432\u0443\u0435\u0442"
    }
}